{"symbol":"ICN","decimals":18,"mainColor":"#8EBFB2","addr":"0x888666ca69e0f178ded6d75b5726cee99a87d698","links":[{"Blog":"https://medium.com/iconominet"},{"CoinMarketCap":"iconomi"},{"Email":"mailto:support@iconomi.net"},{"Facebook":"https://www.facebook.com/iconomi.net/"},{"Reddit":"https://www.reddit.com/r/ICONOMI"},{"Slack":"https://iconominet.slack.com/"},{"Twitter":"https://twitter.com/iconominet"},{"Website":"https://iconomi.net/"},{"Website":"https://www.iconomi.net/"}],"image":"ERC20Tokens/0x888666ca69e0f178ded6d75b5726cee99a87d698/0x888666ca69e0f178ded6d75b5726cee99a87d698.png","description":"Create your own Digital Asset Arrays&trade; (DAA) from a wide variety of digital assets. Manage them and compare your performance with others. Attract supporters and make your mark in the new distributed economy.","name":"ICONOMI"}